persyn/__init__.py
persyn/kill_bot.py
persyn/launch_bot.py
persyn/chat/__init__.py
persyn/chat/common.py
persyn/chat/simple.py
persyn/chat/discord/basic.py
persyn/chat/discord/bot.py
persyn/chat/mastodon/bot.py
persyn/chat/mastodon/login.py
persyn/chat/mastodon/masto-login.py
persyn/chat/mastodon/masto-stream.py
persyn/chat/slack/bot.py
persyn/chat/stdio/add_goal.py
persyn/chat/stdio/elaborate.py
persyn/chat/stdio/import_text.py
persyn/chat/stdio/inject_idea.py
persyn/chat/stdio/opine.py
persyn/chat/stdio/read_rss.py
persyn/chat/stdio/read_url.py
persyn/chat/stdio/send_chat.py
persyn/chat/stdio/summarize.py
persyn/dreams/__init__.py
persyn/dreams/dreams.py
persyn/dreams/receive-sqs.py
persyn/dreams/send-sqs.py
persyn/dreams/stable_diffusion.py
persyn/dreams/clip_interrogator/__init__.py
persyn/dreams/clip_interrogator/interrogator.py
persyn/dreams/prompt-parrot/prompt-parrot.py
persyn/dreams/stylegan2/dataset_tool.py
persyn/dreams/stylegan2/make_a_face.py
persyn/dreams/stylegan2/pretrained_networks.py
persyn/dreams/stylegan2/projector.py
persyn/dreams/stylegan2/run_generator.py
persyn/dreams/stylegan2/run_metrics.py
persyn/dreams/stylegan2/run_projector.py
persyn/dreams/stylegan2/run_training.py
persyn/dreams/stylegan2/dnnlib/__init__.py
persyn/dreams/stylegan2/dnnlib/util.py
persyn/dreams/stylegan2/dnnlib/submission/__init__.py
persyn/dreams/stylegan2/dnnlib/submission/run_context.py
persyn/dreams/stylegan2/dnnlib/submission/submit.py
persyn/dreams/stylegan2/dnnlib/submission/internal/__init__.py
persyn/dreams/stylegan2/dnnlib/submission/internal/local.py
persyn/dreams/stylegan2/dnnlib/tflib/__init__.py
persyn/dreams/stylegan2/dnnlib/tflib/autosummary.py
persyn/dreams/stylegan2/dnnlib/tflib/custom_ops.py
persyn/dreams/stylegan2/dnnlib/tflib/network.py
persyn/dreams/stylegan2/dnnlib/tflib/optimizer.py
persyn/dreams/stylegan2/dnnlib/tflib/tfutil.py
persyn/dreams/stylegan2/dnnlib/tflib/ops/__init__.py
persyn/dreams/stylegan2/dnnlib/tflib/ops/fused_bias_act.py
persyn-0.1.2.dist-info/LICENSE.txt
persyn-0.1.2.dist-info/METADATA
persyn-0.1.2.dist-info/WHEEL
persyn-0.1.2.dist-info/entry_points.txt
persyn-0.1.2.dist-info/top_level.txt
persyn-0.1.2.dist-info/RECORD
