Metadata-Version: 2.1
Name: persyn
Version: 0.1.2
Summary: Personality Syndrome. Persyn for short.
Author-email: Rob Flickenger <rob@hackerfriendly.com>
Project-URL: Homepage, https://persyn.io
Project-URL: Bug Tracker, https://github.com/hackerfriendly/persyn/issues
Classifier: Programming Language :: Python :: 3
Classifier: License :: OSI Approved :: MIT License
Classifier: Operating System :: OS Independent
Requires-Python: >=3.8
License-File: LICENSE.txt
Requires-Dist: aioredis
Requires-Dist: alt-profanity-check (==1.1.3)
Requires-Dist: asyncio
Requires-Dist: beautifulsoup4
Requires-Dist: certifi
Requires-Dist: click
Requires-Dist: coreferee
Requires-Dist: discord.py
Requires-Dist: dotwiz
Requires-Dist: fastapi[all]
Requires-Dist: flair
Requires-Dist: ftfy (==6.1.1)
Requires-Dist: humanize
Requires-Dist: Levenshtein
Requires-Dist: Mastodon.py
Requires-Dist: neomodel
Requires-Dist: nlpcloud
Requires-Dist: nltk
Requires-Dist: openai
Requires-Dist: plotly
Requires-Dist: python-ulid
Requires-Dist: pyyaml
Requires-Dist: redis[hiredis] (>=4.5.0)
Requires-Dist: requests
Requires-Dist: scikit-learn (==1.1.3)
Requires-Dist: scipy (==1.9.0)
Requires-Dist: shortuuid
Requires-Dist: slack-bolt
Requires-Dist: spacy
Requires-Dist: spacytextblob
Requires-Dist: tiktoken
Requires-Dist: uvicorn
Requires-Dist: wikipedia
Provides-Extra: all
Requires-Dist: accelerate ; extra == 'all'
Requires-Dist: diffusers ; extra == 'all'
Requires-Dist: safetensors ; extra == 'all'
Requires-Dist: scipy ; extra == 'all'
Requires-Dist: timm ; extra == 'all'
Requires-Dist: torch ; extra == 'all'
Requires-Dist: torchvision ; extra == 'all'
Requires-Dist: tqdm ; extra == 'all'
Requires-Dist: transformers ; extra == 'all'
Provides-Extra: dev
Requires-Dist: pytest ; extra == 'dev'
Requires-Dist: pylint ; extra == 'dev'
Requires-Dist: jupyterlab ; extra == 'dev'
Provides-Extra: stable_diffusion
Requires-Dist: accelerate ; extra == 'stable_diffusion'
Requires-Dist: scipy ; extra == 'stable_diffusion'
Requires-Dist: safetensors ; extra == 'stable_diffusion'
Requires-Dist: transformers ; extra == 'stable_diffusion'
Requires-Dist: diffusers ; extra == 'stable_diffusion'
Requires-Dist: torch ; extra == 'stable_diffusion'
Requires-Dist: torchvision ; extra == 'stable_diffusion'
